dl_models/__init__.py
dl_models/test.py
dl_models-0.0.3.dist-info/METADATA
dl_models-0.0.3.dist-info/WHEEL
dl_models-0.0.3.dist-info/top_level.txt
dl_models-0.0.3.dist-info/RECORD
